gmft/__init__.py
gmft/auto.py
gmft/base.py
gmft/common.py
gmft/presets.py
gmft/py.typed
gmft/table_detection.py
gmft/table_function.py
gmft/table_function_algorithm.py
gmft/table_visualization.py
gmft/_rich_text/__init__.py
gmft/algorithm/__init__.py
gmft/algorithm/captions.py
gmft/algorithm/dividers.py
gmft/algorithm/histogram.py
gmft/algorithm/structure.py
gmft/core/__init__.py
gmft/core/_dataclasses.py
gmft/core/auto_lazy.py
gmft/core/exception/__init__.py
gmft/core/io/__init__.py
gmft/core/io/serial/dicts.py
gmft/core/legacy/fctn_results.py
gmft/core/legacy/mirror.py
gmft/core/legacy/removed_config.py
gmft/core/ml/__init__.py
gmft/core/ml/prediction/__init__.py
gmft/detectors/__init__.py
gmft/detectors/base.py
gmft/detectors/common.py
gmft/detectors/img2table.py
gmft/detectors/tatr.py
gmft/formatters/__init__.py
gmft/formatters/base.py
gmft/formatters/common.py
gmft/formatters/ditr.py
gmft/formatters/histogram.py
gmft/formatters/img2table.py
gmft/formatters/tatr.py
gmft/formatters/page/__init__.py
gmft/formatters/page/auto.py
gmft/formatters/page/base.py
gmft/formatters/page/components.py
gmft/formatters/page/embed.py
gmft/impl/ditr/config.py
gmft/impl/tatr/config.py
gmft/pdf_bindings/__init__.py
gmft/pdf_bindings/base.py
gmft/pdf_bindings/bindings_pdfium.py
gmft/pdf_bindings/common.py
gmft/pdf_bindings/pdfium.py
gmft/pdf_bindings/pdftext.py
gmft-0.4.2.dist-info/licenses/LICENSE
gmft-0.4.2.dist-info/WHEEL
gmft-0.4.2.dist-info/METADATA
gmft-0.4.2.dist-info/RECORD
