Metadata-Version: 2.4
Name: gmft
Version: 0.4.2
Summary: Lightweight, performant, deep table extraction
Author: conjunct, conjuncts
Requires-Python: >=3.9
Classifier: Development Status :: 4 - Beta
Classifier: License :: OSI Approved :: MIT License
License-File: LICENSE
Requires-Dist: pypdfium2>=4.30.0
Requires-Dist: transformers>=4.35.2
Requires-Dist: torch>=2.5.0
Requires-Dist: pillow
Requires-Dist: pandas
Requires-Dist: matplotlib
Requires-Dist: tabulate>=0.9.0
Requires-Dist: typing_extensions>=4.9
Requires-Dist: img2table>=1.4.1 ; extra == "img2table"
Project-URL: Homepage, https://github.com/conjuncts/gmft
Project-URL: Issues, https://github.com/conjuncts/gmft/issues
Provides-Extra: img2table
